excel4rag/__init__.py
excel4rag/excel_handler.py
excel4rag/table_formatter.py
excel4rag-0.1.3.dist-info/licenses/LICENSE
excel4rag-0.1.3.dist-info/METADATA
excel4rag-0.1.3.dist-info/WHEEL
excel4rag-0.1.3.dist-info/top_level.txt
excel4rag-0.1.3.dist-info/RECORD
