Metadata-Version: 2.4
Name: excel4rag
Version: 0.1.3
Summary: A Python package for extracting tables and key-value pairs from Excel files
Home-page: https://github.com/benmcnicol/excel4rag
Author: Ben
Author-email: benmcnicol@gmail.com
Project-URL: Bug Reports, https://github.com/benmcnicol/excel4rag/issues
Project-URL: Source, https://github.com/benmcnicol/excel4rag
Keywords: excel,tables,json,html,markdown,rag,data extraction
Classifier: Development Status :: 3 - Alpha
Classifier: Intended Audience :: Developers
Classifier: License :: OSI Approved :: MIT License
Classifier: Operating System :: OS Independent
Classifier: Programming Language :: Python :: 3
Classifier: Programming Language :: Python :: 3.8
Classifier: Programming Language :: Python :: 3.9
Classifier: Programming Language :: Python :: 3.10
Classifier: Programming Language :: Python :: 3.11
Classifier: Topic :: Software Development :: Libraries :: Python Modules
Classifier: Topic :: Office/Business :: Office Suites
Classifier: Topic :: Text Processing :: Markup :: HTML
Classifier: Topic :: Text Processing :: Markup :: Markdown
Requires-Python: >=3.8,<3.12
License-File: LICENSE
Requires-Dist: openpyxl<4.0.0,>=3.1.2
Requires-Dist: pandas<3.0.0,>=2.0.3
Requires-Dist: numpy<2.0.0,>=1.24.3
Dynamic: author
Dynamic: author-email
Dynamic: classifier
Dynamic: description
Dynamic: description-content-type
Dynamic: home-page
Dynamic: keywords
Dynamic: license-file
Dynamic: project-url
Dynamic: requires-dist
Dynamic: requires-python
Dynamic: summary
